super_scad_logo/Logo.py
super_scad_logo/__init__.py
super_scad_logo-0.1.0.dist-info/LICENSE
super_scad_logo-0.1.0.dist-info/METADATA
super_scad_logo-0.1.0.dist-info/WHEEL
super_scad_logo-0.1.0.dist-info/RECORD
